rtspbrute/__init__.py
rtspbrute/__main__.py
rtspbrute/credentials.txt
rtspbrute/routes.txt
rtspbrute/modules/__init__.py
rtspbrute/modules/attack.py
rtspbrute/modules/packet.py
rtspbrute/modules/rtsp.py
rtspbrute/modules/utils.py
rtspbrute/modules/worker.py
rtspbrute/modules/cli/__init__.py
rtspbrute/modules/cli/input.py
rtspbrute/modules/cli/output.py
tests/__init__.py
tests/conftest.py
tests/test_attack.py
tests/test_input.py
tests/test_packet.py
tests/test_rtsp.py
tests/test_utils.py
tests/test_worker.py
rtspbrute-1.0.4.dist-info/LICENSE
rtspbrute-1.0.4.dist-info/METADATA
rtspbrute-1.0.4.dist-info/WHEEL
rtspbrute-1.0.4.dist-info/entry_points.txt
rtspbrute-1.0.4.dist-info/top_level.txt
rtspbrute-1.0.4.dist-info/RECORD
