Metadata-Version: 2.1
Name: rtspbrute
Version: 1.0.4
Summary: Tool for RTSP that brute-forces routes and credentials, makes screenshots!
Home-page: https://gitlab.com/woolf/RTSPbrute
Author: Woolf
Author-email: woolf24@protonmail.com
License: UNKNOWN
Project-URL: Source, https://gitlab.com/woolf/RTSPbrute
Project-URL: Tracker, https://gitlab.com/woolf/RTSPbrute/-/issues
Keywords: netstalking rtsp brute cctv
Platform: UNKNOWN
Classifier: Development Status :: 5 - Production/Stable
Classifier: Environment :: Console
Classifier: Intended Audience :: Developers
Classifier: Intended Audience :: Information Technology
Classifier: License :: OSI Approved :: GNU General Public License v3 (GPLv3)
Classifier: Natural Language :: English
Classifier: Operating System :: OS Independent
Classifier: Programming Language :: Python :: 3
Classifier: Programming Language :: Python :: 3.6
Classifier: Programming Language :: Python :: 3.7
Classifier: Programming Language :: Python :: 3.8
Classifier: Programming Language :: Python :: 3.9
Classifier: Topic :: Internet
Classifier: Topic :: Multimedia :: Video :: Capture
Classifier: Topic :: Security
Classifier: Topic :: Utilities
Requires-Python: >=3.6
Requires-Dist: av (<9)
Requires-Dist: Pillow (<9)
Requires-Dist: rich (<11)
